django_cowhite_blog/__init__.py
django_cowhite_blog/admin.py
django_cowhite_blog/apps.py
django_cowhite_blog/models.py
django_cowhite_blog/tests.py
django_cowhite_blog/urls.py
django_cowhite_blog/utils.py
django_cowhite_blog/views.py
django_cowhite_blog/migrations/0001_initial.py
django_cowhite_blog/migrations/0002_auto_20180617_0809.py
django_cowhite_blog/migrations/0003_blogpost_author.py
django_cowhite_blog/migrations/__init__.py
django_cowhite_blog/static/django_cowhite_blog/css/style.css
django_cowhite_blog/static/django_cowhite_blog/fonts/Roboto/LICENSE.txt
django_cowhite_blog/static/django_cowhite_blog/fonts/Roboto/Roboto-Black.ttf
django_cowhite_blog/static/django_cowhite_blog/fonts/Roboto/Roboto-BlackItalic.ttf
django_cowhite_blog/static/django_cowhite_blog/fonts/Roboto/Roboto-Bold.ttf
django_cowhite_blog/static/django_cowhite_blog/fonts/Roboto/Roboto-BoldItalic.ttf
django_cowhite_blog/static/django_cowhite_blog/fonts/Roboto/Roboto-Italic.ttf
django_cowhite_blog/static/django_cowhite_blog/fonts/Roboto/Roboto-Light.ttf
django_cowhite_blog/static/django_cowhite_blog/fonts/Roboto/Roboto-LightItalic.ttf
django_cowhite_blog/static/django_cowhite_blog/fonts/Roboto/Roboto-Medium.ttf
django_cowhite_blog/static/django_cowhite_blog/fonts/Roboto/Roboto-MediumItalic.ttf
django_cowhite_blog/static/django_cowhite_blog/fonts/Roboto/Roboto-Regular.ttf
django_cowhite_blog/static/django_cowhite_blog/fonts/Roboto/Roboto-Thin.ttf
django_cowhite_blog/static/django_cowhite_blog/fonts/Roboto/Roboto-ThinItalic.ttf
django_cowhite_blog/static/django_cowhite_blog/lib/bootstrap-3.3.7-dist/css/bootstrap.min.css
django_cowhite_blog/static/django_cowhite_blog/lib/bootstrap-3.3.7-dist/fonts/glyphicons-halflings-regular.eot
django_cowhite_blog/static/django_cowhite_blog/lib/bootstrap-3.3.7-dist/fonts/glyphicons-halflings-regular.svg
django_cowhite_blog/static/django_cowhite_blog/lib/bootstrap-3.3.7-dist/fonts/glyphicons-halflings-regular.ttf
django_cowhite_blog-0.1.1.dist-info/METADATA
django_cowhite_blog-0.1.1.dist-info/RECORD
django_cowhite_blog-0.1.1.dist-info/WHEEL
django_cowhite_blog-0.1.1.dist-info/top_level.txt
